Workbook

Sheet Assumptions
A1: Financial Model Assumptions
A2: Metric | B2: Bear Case (-20%) | C2: Base Case | D2: Bull Case (+20%)
A3: Monthly ARPU ($) | B3: 7.2 | C3: 9 | D3: 10.8
A4: Target Users (90 Days) | B4: 400 | C4: 500 | D4: 600
A5: Customer Acquisition Cost (CAC) ($) | B5: 60 | C5: 50 | D5: 40
A6: Monthly Churn Rate (%) | B6: 0.1 | C6: 0.08 | D6: 0.06
A7: Gross Margin (%) | B7: 0.7 | C7: 0.75 | D7: 0.8
A8: Monthly Operating Expenses (OpEx) ($) | B8: 2400 | C8: 2000 | D8: 1600

Sheet Financial Model
A1: NutriTrack 90-Day Financial Model
A2: Metric | B2: Bear Case | C2: Base Case | D2: Bull Case
A3: Target Users (End of 90 Days) | B3: =Assumptions!B4 | C3: =Assumptions!C4 | D3: =Assumptions!D4
A4: Monthly ARPU | B4: =Assumptions!B3 | C4: =Assumptions!C3 | D4: =Assumptions!D3
A5: Total MRR (End of 90 Days) | B5: =B3*B4 | C5: =C3*C4 | D5: =D3*D4
A6: Unit Economics
A7: Customer Acquisition Cost (CAC) | B7: =Assumptions!B5 | C7: =Assumptions!C5 | D7: =Assumptions!D5
A8: Lifetime Value (LTV) | B8: =B4*Assumptions!B7/Assumptions!B6 | C8: =C4*Assumptions!C7/Assumptions!C6 | D8: =D4*Assumptions!D7/Assumptions!D6
A9: LTV:CAC Ratio | B9: =B8/B7 | C9: =C8/C7 | D9: =D8/D7
A10: Payback Period (Months) | B10: =B7/(B4*Assumptions!B7) | C10: =C7/(C4*Assumptions!C7) | D10: =D7/(D4*Assumptions!D7)
A11: Profitability (Monthly at 90-day target)
A12: Gross Profit | B12: =B5*Assumptions!B7 | C12: =C5*Assumptions!C7 | D12: =D5*Assumptions!D7
A13: Operating Expenses | B13: =Assumptions!B8 | C13: =Assumptions!C8 | D13: =Assumptions!D8
A14: Net Income | B14: =B12-B13 | C14: =C12-C13 | D14: =D12-D13

Sheet Risk Assessment
A1: NutriTrack Risk Assessment
A2: Risk Name | B2: Category | C2: Probability (1-5) | D2: Impact (1-5) | E2: Risk Score (P x I) | F2: Mitigation
A3: Low LTV:CAC Ratio (Financial Sustainability) | B3: Financial Risk | C3: 4 | D3: 5 | E3: =C3*D3 | F3: Aggressively optimize marketing channels for lower CAC; focus on retention to reduce churn and increase LTV; explore pricing strategies.
A4: Competitive Response/Pricing Pressure | B4: Market Risk | C4: 3 | D4: 4 | E4: =C4*D4 | F4: Differentiate clearly on AI-driven personalization and comprehensive features; monitor competitor pricing; build strong community/brand loyalty.
A5: User Acquisition Target Miss | B5: Execution Risk | C5: 4 | D5: 3 | E5: =C5*D5 | F5: Diversify GTM channels; A/B test marketing messages; closely monitor conversion rates; have contingency plans for marketing spend.
